Metadata-Version: 1.1
Name: sqlibrist
Version: 0.1.10
Summary: Simple tool for managing DB structure, automating patch creation for DB structure migration.
Home-page: https://github.com/condograde/sqlibrist
Author: Serj Zavadsky
Author-email: fevral13@gmail.com
License: MIT License
Keywords: sqlibrist,db structure,sql,schema migration
Platform: UNKNOWN
Classifier: Environment :: Web Environment
Classifier: Environment :: Console
Classifier: Development Status :: 4 - Beta
Classifier: Intended Audience :: Developers
Classifier: Intended Audience :: System Administrators
Classifier: License :: OSI Approved :: MIT License
Classifier: Operating System :: OS Independent
Classifier: Programming Language :: Python
Classifier: Programming Language :: Python :: 2.7
Classifier: Programming Language :: Python :: 3.3
Classifier: Programming Language :: Python :: 3.4
Classifier: Programming Language :: Python :: 3.5
Classifier: Topic :: Database
Classifier: Topic :: Database :: Database Engines/Servers
Classifier: Topic :: Utilities
